LICENSE
MANIFEST.in
README.md
setup.py
demo_dir/__init__.py
demo_dir/demo_1.py
syn_src/__init__.py
syn_src/cmdline.py
syn_src/_ui/__init__.py
syn_src/_ui/choice_dir.py
syn_src/_ui/show_status.py
syn_src/base_cls/__init__.py
syn_src/base_cls/basic_cls.py
syn_src/proc_files/__init__.py
syn_src/proc_files/dir_base.py
syn_src/proc_files/file_base.py
syndir.egg-info/PKG-INFO
syndir.egg-info/SOURCES.txt
syndir.egg-info/dependency_links.txt
syndir.egg-info/entry_points.txt
syndir.egg-info/not-zip-safe
syndir.egg-info/top_level.txt