Metadata-Version: 1.2
Name: syndir
Version: 0.0.2
Summary: 多目录文件同步
Home-page: https://github.com/sixiyizai/syndir
Author: sixi
Author-email: UNKNOWN
License: Apache License
Keywords: synchronization directorys
Platform: UNKNOWN
Classifier: Programming Language :: Python :: 3
Requires-Python: >=3.0.0
